Lattice Diamond/full/raw_frame_capture.v
`timescale 1ns/1ps

module raw_frame_capture #(
    parameter [15:0] FRAME_W = 16'd640,
    parameter [15:0] FRAME_H = 16'd480,
    parameter integer FIFO_AW = 11,
    parameter [31:0] SDRAM_LEVEL_HIGH_WATER = 32'd120000
)(
    input  wire        clk_sys,
    input  wire        rst_sys_n,
    input  wire        pclk,
    input  wire        rst_pclk_n,
    input  wire        vsync,
    input  wire        href,
    input  wire [7:0]  cam_d,
    input  wire        cam_init_done,
    input  wire        capture_enable,
    input  wire [7:0]  frame_stride,

    output reg         frame_ready,
    output reg  [31:0] frame_id,
    output reg  [15:0] frame_w,
    output reg  [15:0] frame_h,
    output reg  [31:0] payload_bytes,
    output reg  [7:0]  stream_kind,

    output reg         sdram_wr_valid,
    output reg  [15:0] sdram_wr_data,
    input  wire        sdram_wr_ready,
    input  wire [31:0] sdram_level_words
);

    localparam integer FIFO_DEPTH = (1 << FIFO_AW);
    localparam [31:0] RAW_BYTES_Y = FRAME_W * FRAME_H;

    localparam [11:0] FRAME_W_12    = FRAME_W[11:0];
    localparam [10:0] FRAME_H_11    = FRAME_H[10:0];
    localparam [11:0] FRAME_W_M2_12 = (FRAME_W > 16'd1) ? (FRAME_W[11:0] - 12'd2) : 12'd0;

    // ============================================================
    // Sync control inputs into pclk domain
    // ============================================================
    reg cam_ok_p1, cam_ok_p2;
    reg cap_en_p1, cap_en_p2;
    reg [7:0] stride_p1, stride_p2;

    wire cam_ok = cam_ok_p2;

    always @(posedge pclk) begin
        if (!rst_pclk_n) begin
            cam_ok_p1 <= 1'b0;
            cam_ok_p2 <= 1'b0;

            cap_en_p1 <= 1'b0;
            cap_en_p2 <= 1'b0;

            stride_p1 <= 8'd1;
            stride_p2 <= 8'd1;
        end else begin
            cam_ok_p1 <= cam_init_done;
            cam_ok_p2 <= cam_ok_p1;

            cap_en_p1 <= capture_enable;
            cap_en_p2 <= cap_en_p1;

            stride_p1 <= frame_stride;
            stride_p2 <= stride_p1;
        end
    end

    // ============================================================
    // PCLK-domain camera byte parsing
    // Keep only Y bytes from YUYV stream
    // ============================================================
    reg [1:0]  yuyv_sub;
    reg [11:0] x_pix;
    reg [10:0] y_line;
    reg        vsync_d, href_d;

    wire href_fall   = (href_d  == 1'b1) && (href  == 1'b0);
    wire frame_start = (vsync_d == 1'b1) && (vsync == 1'b0);
    wire frame_end   = (vsync_d == 1'b0) && (vsync == 1'b1);

    wire y_is_valid  = href && !vsync && ((yuyv_sub == 2'd0) || (yuyv_sub == 2'd2));
    wire in_bounds   = (x_pix < FRAME_W_12) && (y_line < FRAME_H_11);

    reg [7:0]  stride_count_p;
    reg        capture_this_frame_p;
    reg [31:0] frame_ctr_p;
    reg [31:0] active_frame_id_p;

    // frame done pulse/toggle from pclk to sys
    reg        raw_done_tog_p;
    reg [31:0] raw_done_frame_id_p;
    reg        raw_done_pending_p;

    always @(posedge pclk) begin
        if (!rst_pclk_n) begin
            vsync_d <= 1'b1;
            href_d  <= 1'b0;

            yuyv_sub <= 2'd0;
            x_pix    <= 12'd0;
            y_line   <= 11'd0;

            stride_count_p       <= 8'd0;
            capture_this_frame_p <= 1'b0;
            frame_ctr_p          <= 32'd0;
            active_frame_id_p    <= 32'd0;

            raw_done_tog_p      <= 1'b0;
            raw_done_frame_id_p <= 32'd0;
            raw_done_pending_p  <= 1'b0;
        end else begin
            vsync_d <= vsync;
            href_d  <= href;

            // frame start
            if (frame_start) begin
                frame_ctr_p <= frame_ctr_p + 32'd1;

                yuyv_sub <= 2'd0;
                x_pix    <= 12'd0;
                y_line   <= 11'd0;

                if (!cap_en_p2) begin
                    capture_this_frame_p <= 1'b0;
                    stride_count_p       <= 8'd0;
                end else if (stride_count_p == 8'd0) begin
                    capture_this_frame_p <= 1'b1;
                    active_frame_id_p    <= frame_ctr_p + 32'd1;

                    if (stride_p2 <= 8'd1)
                        stride_count_p <= 8'd0;
                    else
                        stride_count_p <= stride_p2 - 8'd1;
                end else begin
                    capture_this_frame_p <= 1'b0;
                    stride_count_p       <= stride_count_p - 8'd1;
                end
            end

            // byte/line tracking while inside active video
            if (!href || vsync) begin
                yuyv_sub <= 2'd0;
                x_pix    <= 12'd0;
            end else begin
                yuyv_sub <= yuyv_sub + 2'd1;

                if (yuyv_sub == 2'd2) begin
                    if (x_pix < FRAME_W_M2_12)
                        x_pix <= x_pix + 12'd2;
                    else
                        x_pix <= 12'd0;
                end
            end

            if (href_fall) begin
                x_pix    <= 12'd0;
                yuyv_sub <= 2'd0;

                if (y_line < (FRAME_H_11 - 11'd1))
                    y_line <= y_line + 11'd1;
                else
                    y_line <= 11'd0;
            end

            // send the toggle one pclk after loading frame id
            if (raw_done_pending_p) begin
                raw_done_tog_p     <= ~raw_done_tog_p;
                raw_done_pending_p <= 1'b0;
            end

            // frame end
            if (frame_end) begin
                if (capture_this_frame_p) begin
                    raw_done_frame_id_p <= active_frame_id_p;
                    raw_done_pending_p  <= 1'b1;
                end
            end
        end
    end

    wire cap_take_byte = cam_ok && capture_this_frame_p && y_is_valid && in_bounds;

    // ============================================================
    // Async FIFO: pclk write side
    // ============================================================
    (* syn_ramstyle = "block_ram" *) reg [7:0] fifo_mem [0:FIFO_DEPTH-1];

    reg [FIFO_AW:0] wptr_bin,  wptr_gray;
    reg [FIFO_AW:0] rptr_bin,  rptr_gray;

    reg [FIFO_AW:0] rptr_gray_w1, rptr_gray_w2;
    reg [FIFO_AW:0] wptr_gray_r1, wptr_gray_r2;

    function [FIFO_AW:0] bin2gray;
        input [FIFO_AW:0] b;
        begin
            bin2gray = (b >> 1) ^ b;
        end
    endfunction

    wire [FIFO_AW:0] rptr_gray_w = rptr_gray_w2;

    wire [FIFO_AW:0] wptr_bin_inc  = wptr_bin + {{FIFO_AW{1'b0}}, 1'b1};
    wire [FIFO_AW:0] wptr_gray_inc = bin2gray(wptr_bin_inc);

    wire fifo_full_next =
        (wptr_gray_inc == {~rptr_gray_w[FIFO_AW:FIFO_AW-1], rptr_gray_w[FIFO_AW-2:0]});

    wire fifo_wready   = ~fifo_full_next;
    wire do_write_pclk = cap_take_byte && fifo_wready;

    wire [FIFO_AW:0] wptr_bin_n  = do_write_pclk ? wptr_bin_inc  : wptr_bin;
    wire [FIFO_AW:0] wptr_gray_n = do_write_pclk ? wptr_gray_inc : wptr_gray;

    always @(posedge pclk) begin
        if (!rst_pclk_n) begin
            wptr_bin     <= {FIFO_AW+1{1'b0}};
            wptr_gray    <= {FIFO_AW+1{1'b0}};
            rptr_gray_w1 <= {FIFO_AW+1{1'b0}};
            rptr_gray_w2 <= {FIFO_AW+1{1'b0}};
        end else begin
            rptr_gray_w1 <= rptr_gray;
            rptr_gray_w2 <= rptr_gray_w1;

            if (do_write_pclk) begin
                fifo_mem[wptr_bin[FIFO_AW-1:0]] <= cam_d;
                wptr_bin  <= wptr_bin_n;
                wptr_gray <= wptr_gray_n;
            end
        end
    end

    // ============================================================
    // Async FIFO: sys read side
    // ============================================================
    wire [FIFO_AW:0] wptr_gray_r = wptr_gray_r2;
    wire fifo_empty = (rptr_gray == wptr_gray_r);

    reg [7:0] fifo_rdata;
    reg       fifo_rvalid;
    reg       fifo_rpop;
    reg       fifo_rpop_d;

    // packer
    reg [7:0] pack_lo;
    reg       pack_half;

    wire can_issue_word = (!sdram_wr_valid) || sdram_wr_ready;

    // ============================================================
    // PCLK -> SYS metadata CDC
    // ============================================================
    reg        raw_done_s1, raw_done_s2, raw_done_s3;
    reg [31:0] raw_done_frame_id_s1, raw_done_frame_id_s2, raw_done_frame_id_s3;

    wire raw_done_pulse_sys = (raw_done_s3 != raw_done_s2);

    always @(posedge clk_sys) begin
        if (!rst_sys_n) begin
            // FIFO side
            rptr_bin      <= {FIFO_AW+1{1'b0}};
            rptr_gray     <= {FIFO_AW+1{1'b0}};
            wptr_gray_r1  <= {FIFO_AW+1{1'b0}};
            wptr_gray_r2  <= {FIFO_AW+1{1'b0}};
            fifo_rdata    <= 8'h00;
            fifo_rvalid   <= 1'b0;
            fifo_rpop     <= 1'b0;
            fifo_rpop_d   <= 1'b0;

            // pack/output
            pack_lo        <= 8'h00;
            pack_half      <= 1'b0;
            sdram_wr_valid <= 1'b0;
            sdram_wr_data  <= 16'h0000;

            // metadata
            frame_ready    <= 1'b0;
            frame_id       <= 32'd0;
            frame_w        <= 16'd0;
            frame_h        <= 16'd0;
            payload_bytes  <= 32'd0;
            stream_kind    <= 8'd0;

            raw_done_s1 <= 1'b0;
            raw_done_s2 <= 1'b0;
            raw_done_s3 <= 1'b0;

            raw_done_frame_id_s1 <= 32'd0;
            raw_done_frame_id_s2 <= 32'd0;
            raw_done_frame_id_s3 <= 32'd0;
        end else begin
            // defaults
            frame_ready <= 1'b0;
            fifo_rpop   <= 1'b0;

            // sync FIFO write pointer into sys domain
            wptr_gray_r1 <= wptr_gray;
            wptr_gray_r2 <= wptr_gray_r1;
            fifo_rvalid  <= ~fifo_empty;

            // sync done toggle + frame id into sys domain
            raw_done_s1 <= raw_done_tog_p;
            raw_done_s2 <= raw_done_s1;
            raw_done_s3 <= raw_done_s2;

            raw_done_frame_id_s1 <= raw_done_frame_id_p;
            raw_done_frame_id_s2 <= raw_done_frame_id_s1;
            raw_done_frame_id_s3 <= raw_done_frame_id_s2;

            // frame metadata pulse
            if (raw_done_pulse_sys) begin
                frame_ready   <= 1'b1;
                frame_id      <= raw_done_frame_id_s3;
                frame_w       <= FRAME_W;
                frame_h       <= FRAME_H;
                payload_bytes <= RAW_BYTES_Y;
                stream_kind   <= 8'd2;
            end

            // clear output valid after handshake
            if (sdram_wr_valid && sdram_wr_ready)
                sdram_wr_valid <= 1'b0;

            // remember whether a pop was requested in previous cycle
            fifo_rpop_d <= fifo_rpop;

            // actual FIFO read
            if (fifo_rpop && fifo_rvalid) begin
                fifo_rdata <= fifo_mem[rptr_bin[FIFO_AW-1:0]];
                rptr_bin   <= rptr_bin + {{FIFO_AW{1'b0}}, 1'b1};
                rptr_gray  <= bin2gray(rptr_bin + {{FIFO_AW{1'b0}}, 1'b1});
            end

            // consume returned byte from previous pop
            if (fifo_rpop_d) begin
                if (!pack_half) begin
                    pack_lo   <= fifo_rdata;
                    pack_half <= 1'b1;
                end else if (can_issue_word) begin
                    sdram_wr_data  <= {fifo_rdata, pack_lo};
                    sdram_wr_valid <= 1'b1;
                    pack_half      <= 1'b0;
                end
            end

            // request next byte only when allowed
            if ((sdram_level_words <= SDRAM_LEVEL_HIGH_WATER) &&
                !fifo_rpop_d &&
                fifo_rvalid &&
                (!pack_half || can_issue_word)) begin
                fifo_rpop <= 1'b1;
            end
        end
    end

endmodule

raw_frame_capture.vcd
$version Generated by VerilatedVcd $end
$timescale 1ps $end
 $scope module TOP $end
  $var wire 1 ` clk_sys $end
  $var wire 1 a rst_sys_n $end
  $var wire 1 b pclk $end
  $var wire 1 c rst_pclk_n $end
  $var wire 1 d vsync $end
  $var wire 1 e href $end
  $var wire 8 f cam_d [7:0] $end
  $var wire 1 g cam_init_done $end
  $var wire 1 h capture_enable $end
  $var wire 8 i frame_stride [7:0] $end
  $var wire 1 j frame_ready $end
  $var wire 32 k frame_id [31:0] $end
  $var wire 16 l frame_w [15:0] $end
  $var wire 16 m frame_h [15:0] $end
  $var wire 32 n payload_bytes [31:0] $end
  $var wire 8 o stream_kind [7:0] $end
  $var wire 1 p sdram_wr_valid $end
  $var wire 16 q sdram_wr_data [15:0] $end
  $var wire 1 r sdram_wr_ready $end
  $var wire 32 s sdram_level_words [31:0] $end
  $scope module raw_frame_capture $end
   $var wire 16 } FRAME_W [15:0] $end
   $var wire 16 ~ FRAME_H [15:0] $end
   $var wire 32 !! FIFO_AW [31:0] $end
   $var wire 32 "! SDRAM_LEVEL_HIGH_WATER [31:0] $end
   $var wire 1 ` clk_sys $end
   $var wire 1 a rst_sys_n $end
   $var wire 1 b pclk $end
   $var wire 1 c rst_pclk_n $end
   $var wire 1 d vsync $end
   $var wire 1 e href $end
   $var wire 8 f cam_d [7:0] $end
   $var wire 1 g cam_init_done $end
   $var wire 1 h capture_enable $end
   $var wire 8 i frame_stride [7:0] $end
   $var wire 1 j frame_ready $end
   $var wire 32 k frame_id [31:0] $end
   $var wire 16 l frame_w [15:0] $end
   $var wire 16 m frame_h [15:0] $end
   $var wire 32 n payload_bytes [31:0] $end
   $var wire 8 o stream_kind [7:0] $end
   $var wire 1 p sdram_wr_valid $end
   $var wire 16 q sdram_wr_data [15:0] $end
   $var wire 1 r sdram_wr_ready $end
   $var wire 32 s sdram_level_words [31:0] $end
   $var wire 32 #! FIFO_DEPTH [31:0] $end
   $var wire 32 $! RAW_BYTES_Y [31:0] $end
   $var wire 12 %! FRAME_W_12 [11:0] $end
   $var wire 11 &! FRAME_H_11 [10:0] $end
   $var wire 12 '! FRAME_W_M2_12 [11:0] $end
   $var wire 1 # cam_ok_p1 $end
   $var wire 1 $ cam_ok_p2 $end
   $var wire 1 C cap_en_p1 $end
   $var wire 1 D cap_en_p2 $end
   $var wire 8 E stride_p1 [7:0] $end
   $var wire 8 F stride_p2 [7:0] $end
   $var wire 1 $ cam_ok $end
   $var wire 2 % yuyv_sub [1:0] $end
   $var wire 12 & x_pix [11:0] $end
   $var wire 11 ' y_line [10:0] $end
   $var wire 1 G vsync_d $end
   $var wire 1 ( href_d $end
   $var wire 1 t href_fall $end
   $var wire 1 u frame_start $end
   $var wire 1 v frame_end $end
   $var wire 1 w y_is_valid $end
   $var wire 1 ) in_bounds $end
   $var wire 8 H stride_count_p [7:0] $end
   $var wire 1 I capture_this_frame_p $end
   $var wire 32 J frame_ctr_p [31:0] $end
   $var wire 32 K active_frame_id_p [31:0] $end
   $var wire 1 L raw_done_tog_p $end
   $var wire 32 M raw_done_frame_id_p [31:0] $end
   $var wire 1 N raw_done_pending_p $end
   $var wire 1 x cap_take_byte $end
   $var wire 8 O fifo_mem[0] [7:0] $end
   $var wire 8 P fifo_mem[1] [7:0] $end
   $var wire 8 Q fifo_mem[2] [7:0] $end
   $var wire 8 R fifo_mem[3] [7:0] $end
   $var wire 8 S fifo_mem[4] [7:0] $end
   $var wire 8 T fifo_mem[5] [7:0] $end
   $var wire 8 U fifo_mem[6] [7:0] $end
   $var wire 8 V fifo_mem[7] [7:0] $end
   $var wire 8 W fifo_mem[8] [7:0] $end
   $var wire 8 X fifo_mem[9] [7:0] $end
   $var wire 8 Y fifo_mem[10] [7:0] $end
   $var wire 8 Z fifo_mem[11] [7:0] $end
   $var wire 8 [ fifo_mem[12] [7:0] $end
   $var wire 8 \ fifo_mem[13] [7:0] $end
   $var wire 8 ] fifo_mem[14] [7:0] $end
   $var wire 8 ^ fifo_mem[15] [7:0] $end
   $var wire 5 * wptr_bin [4:0] $end
   $var wire 5 _ wptr_gray [4:0] $end
   $var wire 5 1 rptr_bin [4:0] $end
   $var wire 5 2 rptr_gray [4:0] $end
   $var wire 5 + rptr_gray_w1 [4:0] $end
   $var wire 5 , rptr_gray_w2 [4:0] $end
   $var wire 5 3 wptr_gray_r1 [4:0] $end
   $var wire 5 4 wptr_gray_r2 [4:0] $end
   $var wire 5 , rptr_gray_w [4:0] $end
   $var wire 5 - wptr_bin_inc [4:0] $end
   $var wire 5 . wptr_gray_inc [4:0] $end
   $var wire 1 / fifo_full_next $end
   $var wire 1 0 fifo_wready $end
   $var wire 1 y do_write_pclk $end
   $var wire 5 z wptr_bin_n [4:0] $end
   $var wire 5 { wptr_gray_n [4:0] $end
   $var wire 5 4 wptr_gray_r [4:0] $end
   $var wire 1 5 fifo_empty $end
   $var wire 8 6 fifo_rdata [7:0] $end
   $var wire 1 7 fifo_rvalid $end
   $var wire 1 8 fifo_rpop $end
   $var wire 1 9 fifo_rpop_d $end
   $var wire 8 : pack_lo [7:0] $end
   $var wire 1 ; pack_half $end
   $var wire 1 | can_issue_word $end
   $var wire 1 < raw_done_s1 $end
   $var wire 1 = raw_done_s2 $end
   $var wire 1 > raw_done_s3 $end
   $var wire 32 ? raw_done_frame_id_s1 [31:0] $end
   $var wire 32 @ raw_done_frame_id_s2 [31:0] $end
   $var wire 32 A raw_done_frame_id_s3 [31:0] $end
   $var wire 1 B raw_done_pulse_sys $end
  $upscope $end
 $upscope $end
$enddefinitions $end


#0
0#
0$
b00 %
b000000000000 &
b00000000000 '
0(
1)
b00000 *
b00000 +
b00000 ,
b00001 -
b00001 .
0/
10
b00000 1
b00000 2
b00000 3
b00000 4
15
b00000000 6
07
08
09
b00000000 :
0;
0<
0=
0>
b00000000000000000000000000000000 ?
b00000000000000000000000000000000 @
b00000000000000000000000000000000 A
0B
0C
0D
b00000000 E
b00000000 F
0G
b00000000 H
0I
b00000000000000000000000000000000 J
b00000000000000000000000000000000 K
0L
b00000000000000000000000000000000 M
0N
b00000000 O
b00000000 P
b00000000 Q
b00000000 R
b00000000 S
b00000000 T
b00000000 U
b00000000 V
b00000000 W
b00000000 X
b00000000 Y
b00000000 Z
b00000000 [
b00000000 \
b00000000 ]
b00000000 ^
b00000 _
0`
0a
0b
0c
1d
0e
b00000000 f
0g
0h
b00000001 i
0j
b00000000000000000000000000000000 k
b0000000000000000 l
b0000000000000000 m
b00000000000000000000000000000000 n
b00000000 o
0p
b0000000000000000 q
1r
b00000000000000000000000000000000 s
0t
0u
1v
0w
0x
0y
b00000 z
b00000 {
1|
b0000000000000100 }
b0000000000000010 ~
b00000000000000000000000000000100 !!
b00000000000000011101010011000000 "!
b00000000000000000000000000010000 #!
b00000000000000000000000000001000 $!
b000000000100 %!
b00000000010 &!
b000000000010 '!
#1
b00000001 E
b00000001 F
1G
1`
1b
0v
#2
0`
0b
#3
1`
1b
#4
0`
0b
#5
1`
1b
#6
0`
0b
#7
1`
1b
#8
0`
0b
#9
1`
1b
#10
0`
0b
#11
1`
1b
#12
0`
0b
#13
1`
1b
#14
0`
0b
#15
1`
1b
#16
0`
1a
0b
1c
1g
1h
#17
1#
1C
1`
1b
#18
0`
0b
#19
1$
1D
1`
1b
#20
0`
0b
#21
1`
1b
#22
0`
0b
#23
1`
1b
#24
0`
0b
0d
1u
#25
0G
1I
b00000000000000000000000000000001 J
b00000000000000000000000000000001 K
1`
1b
0u
#26
0`
0b
#27
1`
1b
#28
0`
0b
1e
b00010001 f
1w
1x
1y
b00001 z
b00001 {
#29
b01 %
1(
b00001 *
b00010 -
b00011 .
b00010001 O
b00001 _
1`
1b
0w
0x
0y
#30
0`
0b
b10101010 f
#31
b10 %
b00001 3
1`
1b
1w
1x
1y
b00010 z
b00011 {
#32
0`
0b
b00100010 f
#33
b11 %
b000000000010 &
b00010 *
b00011 -
b00010 .
b00001 4
05
b00100010 P
b00011 _
1`
1b
0w
0x
0y
#34
0`
0b
b10111011 f
#35
b00 %
b00011 3
17
1`
1b
1w
1x
1y
b00011 z
b00010 {
#36
0`
0b
b00110011 f
#37
b01 %
b00011 *
b00100 -
b00110 .
b00011 4
18
b00110011 Q
b00010 _
1`
1b
0w
0x
0y
#38
0`
0b
b11001100 f
#39
b10 %
b00001 1
b00001 2
b00010 3
b00010001 6
19
1`
1b
1w
1x
1y
b00100 z
b00110 {
#40
0`
0b
b01000100 f
#41
b11 %
b000000000000 &
b00100 *
b00001 +
b00101 -
b00111 .
b00010 1
b00011 2
b00010 4
b00100010 6
08
b00010001 :
1;
b01000100 R
b00110 _
1`
1b
0w
0x
0y
#42
0`
0b
b11011101 f
#43
b00 %
b00011 +
b00001 ,
b00110 3
09
0;
1`
1b
1p
b0010001000010001 q
1w
1x
1y
b00101 z
b00111 {
#44
0`
0b
0e
b00000000 f
1t
0w
0x
0y
b00100 z
b00110 {
#45
b00000000001 '
0(
b00011 ,
b00110 4
18
1`
1b
0p
0t
#46
0`
0b
#47
b00011 1
b00010 2
b00110011 6
19
1`
1b
#48
0`
0b
1e
b01010101 f
1w
1x
1y
b00101 z
b00111 {
#49
b01 %
1(
b00101 *
b00010 +
b00110 -
b00101 .
b00100 1
b00110 2
15
b01000100 6
08
b00110011 :
1;
b01010101 S
b00111 _
1`
1b
0w
0x
0y
#50
0`
0b
b11101110 f
#51
b10 %
b00110 +
b00010 ,
b00111 3
07
09
0;
1`
1b
1p
b0100010000110011 q
1w
1x
1y
b00110 z
b00101 {
#52
0`
0b
b01100110 f
#53
b11 %
b000000000010 &
b00110 *
b00110 ,
b00111 -
b00100 .
b00111 4
05
b01100110 T
b00101 _
1`
1b
0p
0w
0x
0y
#54
0`
0b
b11111111 f
#55
b00 %
b00101 3
17
1`
1b
1w
1x
1y
b00111 z
b00100 {
#56
0`
0b
b01110111 f
#57
b01 %
b00111 *
b01000 -
b01100 .
b00101 4
18
b01110111 U
b00100 _
1`
1b
0w
0x
0y
#58
0`
0b
b00010010 f
#59
b10 %
b00101 1
b00111 2
b00100 3
b01010101 6
19
1`
1b
1w
1x
1y
b01000 z
b01100 {
#60
0`
0b
b10001000 f
#61
b11 %
b000000000000 &
b01000 *
b00111 +
b01001 -
b01101 .
b00110 1
b00101 2
b00100 4
b01100110 6
08
b01010101 :
1;
b10001000 V
b01100 _
1`
1b
0w
0x
0y
#62
0`
0b
b00110100 f
#63
b00 %
b00101 +
b00111 ,
b01100 3
09
0;
1`
1b
1p
b0110011001010101 q
1w
1x
1y
b01001 z
b01101 {
#64
0`
0b
0e
b00000000 f
1t
0w
0x
0y
b01000 z
b01100 {
#65
b00000000000 '
0(
b00101 ,
b01100 4
18
1`
1b
0p
0t
#66
0`
0b
1d
1v
#67
b00111 1
b00100 2
b01110111 6
19
1G
b00000000000000000000000000000001 M
1N
1`
1b
0v
#68
0`
0b
#69
b00100 +
b01000 1
b01100 2
15
b10001000 6
08
b01110111 :
1;
b00000000000000000000000000000001 ?
1L
0N
1`
1b
#70
0`
0b
#71
b01100 +
b00100 ,
07
09
0;
1<
b00000000000000000000000000000001 @
1`
1b
1p
b1000100001110111 q
#72
0`
0b
#73
b01100 ,
1=
b00000000000000000000000000000001 A
1B
1`
1b
0p
#74
0`
0b
#75
1>
0B
1`
1b
1j
b00000000000000000000000000000001 k
b0000000000000100 l
b0000000000000010 m
b00000000000000000000000000001000 n
b00000010 o
#76
0`
0b
#77
1`
1b
0j
