Lattice Diamond/full/uart_tx.v
`timescale 1ns/1ps

module uart_tx #(
    parameter integer CLKS_PER_BIT = 1667
)(
    input  wire       clk,
    input  wire       rst_n,
    input  wire [7:0] data_in,
    input  wire       start,
    output reg        tx,
    output reg        busy,
    output reg        done
);
    localparam [1:0] ST_IDLE  = 2'd0;
    localparam [1:0] ST_START = 2'd1;
    localparam [1:0] ST_DATA  = 2'd2;
    localparam [1:0] ST_STOP  = 2'd3;

    localparam [15:0] CLKS_PER_BIT_M1 = CLKS_PER_BIT - 1;

    reg [1:0]  st;
    reg [15:0] clk_cnt;
    reg [2:0]  bit_idx;
    reg [7:0]  shreg;

    always @(posedge clk) begin
        if (!rst_n) begin
            st      <= ST_IDLE;
            clk_cnt <= 16'd0;
            bit_idx <= 3'd0;
            shreg   <= 8'd0;
            tx      <= 1'b1;
            busy    <= 1'b0;
            done    <= 1'b0;
        end else begin
            done <= 1'b0;

            case (st)
                ST_IDLE: begin
                    tx      <= 1'b1;
                    busy    <= 1'b0;
                    clk_cnt <= 16'd0;
                    bit_idx <= 3'd0;
                    if (start) begin
                        shreg <= data_in;
                        busy  <= 1'b1;
                        st    <= ST_START;
                    end
                end

                ST_START: begin
                    tx   <= 1'b0;
                    busy <= 1'b1;
                    if (clk_cnt == CLKS_PER_BIT_M1) begin
                        clk_cnt <= 16'd0;
                        st      <= ST_DATA;
                    end else begin
                        clk_cnt <= clk_cnt + 16'd1;
                    end
                end

                ST_DATA: begin
                    tx   <= shreg[bit_idx];
                    busy <= 1'b1;
                    if (clk_cnt == CLKS_PER_BIT_M1) begin
                        clk_cnt <= 16'd0;
                        if (bit_idx == 3'd7) begin
                            bit_idx <= 3'd0;
                            st      <= ST_STOP;
                        end else begin
                            bit_idx <= bit_idx + 3'd1;
                        end
                    end else begin
                        clk_cnt <= clk_cnt + 16'd1;
                    end
                end

                ST_STOP: begin
                    tx   <= 1'b1;
                    busy <= 1'b1;
                    if (clk_cnt == CLKS_PER_BIT_M1) begin
                        clk_cnt <= 16'd0;
                        done    <= 1'b1;
                        st      <= ST_IDLE;
                    end else begin
                        clk_cnt <= clk_cnt + 16'd1;
                    end
                end

                default: begin
                    st      <= ST_IDLE;
                    clk_cnt <= 16'd0;
                    bit_idx <= 3'd0;
                    shreg   <= 8'd0;
                    tx      <= 1'b1;
                    busy    <= 1'b0;
                    done    <= 1'b0;
                end
            endcase
        end
    end
endmodule

archive/generated/vcd/uart_tx.vcd
$version Generated by VerilatedVcd $end
$timescale 1ps $end
 $scope module TOP $end
  $var wire 1 ' clk $end
  $var wire 1 ( rst_n $end
  $var wire 8 ) data_in [7:0] $end
  $var wire 1 * start $end
  $var wire 1 + tx $end
  $var wire 1 , busy $end
  $var wire 1 - done $end
  $scope module uart_tx $end
   $var wire 32 . CLKS_PER_BIT [31:0] $end
   $var wire 1 ' clk $end
   $var wire 1 ( rst_n $end
   $var wire 8 ) data_in [7:0] $end
   $var wire 1 * start $end
   $var wire 1 + tx $end
   $var wire 1 , busy $end
   $var wire 1 - done $end
   $var wire 2 / ST_IDLE [1:0] $end
   $var wire 2 0 ST_START [1:0] $end
   $var wire 2 1 ST_DATA [1:0] $end
   $var wire 2 2 ST_STOP [1:0] $end
   $var wire 16 3 CLKS_PER_BIT_M1 [15:0] $end
   $var wire 2 # st [1:0] $end
   $var wire 16 $ clk_cnt [15:0] $end
   $var wire 3 % bit_idx [2:0] $end
   $var wire 8 & shreg [7:0] $end
  $upscope $end
 $upscope $end
$enddefinitions $end


#0
b00 #
b0000000000000000 $
b000 %
b00000000 &
0'
0(
b00000000 )
0*
0+
0,
0-
b00000000000000000000000000001000 .
b00 /
b01 0
b10 1
b11 2
b0000000000000111 3
#1
1'
1+
#2
0'
#3
1'
#4
0'
#5
1'
#6
0'
#7
1'
#8
0'
1(
#9
1'
#10
0'
#11
1'
#12
0'
#13
1'
#14
0'
#15
1'
#16
0'
b10100101 )
1*
#17
b01 #
b10100101 &
1'
1,
#18
0'
0*
#19
b0000000000000001 $
1'
0+
#20
0'
#21
b0000000000000010 $
1'
#22
0'
#23
b0000000000000011 $
1'
#24
0'
#25
b0000000000000100 $
1'
#26
0'
#27
b0000000000000101 $
1'
#28
0'
#29
b0000000000000110 $
1'
#30
0'
#31
b0000000000000111 $
1'
#32
0'
#33
b10 #
b0000000000000000 $
1'
#34
0'
#35
b0000000000000001 $
1'
1+
#36
0'
#37
b0000000000000010 $
1'
#38
0'
#39
b0000000000000011 $
1'
#40
0'
#41
b0000000000000100 $
1'
#42
0'
#43
b0000000000000101 $
1'
#44
0'
#45
b0000000000000110 $
1'
#46
0'
#47
b0000000000000111 $
1'
#48
0'
#49
b0000000000000000 $
b001 %
1'
#50
0'
#51
b0000000000000001 $
1'
0+
#52
0'
#53
b0000000000000010 $
1'
#54
0'
#55
b0000000000000011 $
1'
#56
0'
#57
b0000000000000100 $
1'
#58
0'
#59
b0000000000000101 $
1'
#60
0'
#61
b0000000000000110 $
1'
#62
0'
#63
b0000000000000111 $
1'
#64
0'
#65
b0000000000000000 $
b010 %
1'
#66
0'
#67
b0000000000000001 $
1'
1+
#68
0'
#69
b0000000000000010 $
1'
#70
0'
#71
b0000000000000011 $
1'
#72
0'
#73
b0000000000000100 $
1'
#74
0'
#75
b0000000000000101 $
1'
#76
0'
#77
b0000000000000110 $
1'
#78
0'
#79
b0000000000000111 $
1'
#80
0'
#81
b0000000000000000 $
b011 %
1'
#82
0'
#83
b0000000000000001 $
1'
0+
#84
0'
#85
b0000000000000010 $
1'
#86
0'
#87
b0000000000000011 $
1'
#88
0'
#89
b0000000000000100 $
1'
#90
0'
#91
b0000000000000101 $
1'
#92
0'
#93
b0000000000000110 $
1'
#94
0'
#95
b0000000000000111 $
1'
#96
0'
#97
b0000000000000000 $
b100 %
1'
#98
0'
#99
b0000000000000001 $
1'
#100
0'
#101
b0000000000000010 $
1'
#102
0'
#103
b0000000000000011 $
1'
#104
0'
#105
b0000000000000100 $
1'
#106
0'
#107
b0000000000000101 $
1'
#108
0'
#109
b0000000000000110 $
1'
#110
0'
#111
b0000000000000111 $
1'
#112
0'
#113
b0000000000000000 $
b101 %
1'
#114
0'
#115
b0000000000000001 $
1'
1+
#116
0'
#117
b0000000000000010 $
1'
#118
0'
#119
b0000000000000011 $
1'
#120
0'
#121
b0000000000000100 $
1'
#122
0'
#123
b0000000000000101 $
1'
#124
0'
#125
b0000000000000110 $
1'
#126
0'
#127
b0000000000000111 $
1'
#128
0'
#129
b0000000000000000 $
b110 %
1'
#130
0'
#131
b0000000000000001 $
1'
0+
#132
0'
#133
b0000000000000010 $
1'
#134
0'
#135
b0000000000000011 $
1'
#136
0'
#137
b0000000000000100 $
1'
#138
0'
#139
b0000000000000101 $
1'
#140
0'
#141
b0000000000000110 $
1'
#142
0'
#143
b0000000000000111 $
1'
#144
0'
#145
b0000000000000000 $
b111 %
1'
#146
0'
#147
b0000000000000001 $
1'
1+
#148
0'
#149
b0000000000000010 $
1'
#150
0'
#151
b0000000000000011 $
1'
#152
0'
#153
b0000000000000100 $
1'
#154
0'
#155
b0000000000000101 $
1'
#156
0'
#157
b0000000000000110 $
1'
#158
0'
#159
b0000000000000111 $
1'
#160
0'
#161
b11 #
b0000000000000000 $
b000 %
1'
#162
0'
#163
b0000000000000001 $
1'
#164
0'
#165
b0000000000000010 $
1'
#166
0'
#167
b0000000000000011 $
1'
#168
0'
#169
b0000000000000100 $
1'
#170
0'
#171
b0000000000000101 $
1'
#172
0'
#173
b0000000000000110 $
1'
#174
0'
#175
b0000000000000111 $
1'
#176
0'
#177
b00 #
b0000000000000000 $
1'
1-
#178
0'
#179
1'
0,
0-
