Lattice Diamond/full/uart_rx.v
`timescale 1ns/1ps

module uart_rx #(
    parameter integer CLKS_PER_BIT = 1667
)(
    input  wire clk,
    input  wire rst_n,
    input  wire rx,
    output reg  [7:0] data_out,
    output reg        valid
);
    localparam ST_IDLE  = 2'd0;
    localparam ST_START = 2'd1;
    localparam ST_DATA  = 2'd2;
    localparam ST_STOP  = 2'd3;

    reg [1:0] st;
    reg [15:0] clk_cnt;
    reg [2:0] bit_idx;
    reg [7:0] shreg;
    reg rx_s1, rx_s2;

    always @(posedge clk) begin
        if (!rst_n) begin
            rx_s1 <= 1'b1;
            rx_s2 <= 1'b1;
        end else begin
            rx_s1 <= rx;
            rx_s2 <= rx_s1;
        end
    end

    always @(posedge clk) begin
        if (!rst_n) begin
            st <= ST_IDLE;
            clk_cnt <= 16'd0;
            bit_idx <= 3'd0;
            shreg <= 8'd0;
            data_out <= 8'd0;
            valid <= 1'b0;
        end else begin
            valid <= 1'b0;
            case (st)
                ST_IDLE: begin
                    clk_cnt <= 16'd0;
                    bit_idx <= 3'd0;
                    if (rx_s2 == 1'b0) st <= ST_START;
                end
                ST_START: begin
                    if (clk_cnt == ((CLKS_PER_BIT-1)/2)) begin
                        if (rx_s2 == 1'b0) begin
                            clk_cnt <= 16'd0;
                            st <= ST_DATA;
                        end else begin
                            st <= ST_IDLE;
                        end
                    end else begin
                        clk_cnt <= clk_cnt + 16'd1;
                    end
                end
                ST_DATA: begin
                    if (clk_cnt == CLKS_PER_BIT-1) begin
                        clk_cnt <= 16'd0;
                        shreg[bit_idx] <= rx_s2;
                        if (bit_idx == 3'd7) begin
                            bit_idx <= 3'd0;
                            st <= ST_STOP;
                        end else begin
                            bit_idx <= bit_idx + 3'd1;
                        end
                    end else begin
                        clk_cnt <= clk_cnt + 16'd1;
                    end
                end
                ST_STOP: begin
                    if (clk_cnt == CLKS_PER_BIT-1) begin
                        clk_cnt <= 16'd0;
                        if (rx_s2 == 1'b1) begin
                            data_out <= shreg;
                            valid <= 1'b1;
                        end
                        st <= ST_IDLE;
                    end else begin
                        clk_cnt <= clk_cnt + 16'd1;
                    end
                end
                default: st <= ST_IDLE;
            endcase
        end
    end
endmodule

Lattice Diamond/full/uart_tx.v
`timescale 1ns/1ps

module uart_tx #(
    parameter integer CLKS_PER_BIT = 1667
)(
    input  wire       clk,
    input  wire       rst_n,
    input  wire [7:0] data_in,
    input  wire       start,
    output reg        tx,
    output reg        busy,
    output reg        done
);
    localparam [1:0] ST_IDLE  = 2'd0;
    localparam [1:0] ST_START = 2'd1;
    localparam [1:0] ST_DATA  = 2'd2;
    localparam [1:0] ST_STOP  = 2'd3;

    localparam [15:0] CLKS_PER_BIT_M1 = CLKS_PER_BIT - 1;

    reg [1:0]  st;
    reg [15:0] clk_cnt;
    reg [2:0]  bit_idx;
    reg [7:0]  shreg;

    always @(posedge clk) begin
        if (!rst_n) begin
            st      <= ST_IDLE;
            clk_cnt <= 16'd0;
            bit_idx <= 3'd0;
            shreg   <= 8'd0;
            tx      <= 1'b1;
            busy    <= 1'b0;
            done    <= 1'b0;
        end else begin
            done <= 1'b0;

            case (st)
                ST_IDLE: begin
                    tx      <= 1'b1;
                    busy    <= 1'b0;
                    clk_cnt <= 16'd0;
                    bit_idx <= 3'd0;
                    if (start) begin
                        shreg <= data_in;
                        busy  <= 1'b1;
                        st    <= ST_START;
                    end
                end

                ST_START: begin
                    tx   <= 1'b0;
                    busy <= 1'b1;
                    if (clk_cnt == CLKS_PER_BIT_M1) begin
                        clk_cnt <= 16'd0;
                        st      <= ST_DATA;
                    end else begin
                        clk_cnt <= clk_cnt + 16'd1;
                    end
                end

                ST_DATA: begin
                    tx   <= shreg[bit_idx];
                    busy <= 1'b1;
                    if (clk_cnt == CLKS_PER_BIT_M1) begin
                        clk_cnt <= 16'd0;
                        if (bit_idx == 3'd7) begin
                            bit_idx <= 3'd0;
                            st      <= ST_STOP;
                        end else begin
                            bit_idx <= bit_idx + 3'd1;
                        end
                    end else begin
                        clk_cnt <= clk_cnt + 16'd1;
                    end
                end

                ST_STOP: begin
                    tx   <= 1'b1;
                    busy <= 1'b1;
                    if (clk_cnt == CLKS_PER_BIT_M1) begin
                        clk_cnt <= 16'd0;
                        done    <= 1'b1;
                        st      <= ST_IDLE;
                    end else begin
                        clk_cnt <= clk_cnt + 16'd1;
                    end
                end

                default: begin
                    st      <= ST_IDLE;
                    clk_cnt <= 16'd0;
                    bit_idx <= 3'd0;
                    shreg   <= 8'd0;
                    tx      <= 1'b1;
                    busy    <= 1'b0;
                    done    <= 1'b0;
                end
            endcase
        end
    end
endmodule

Lattice Diamond/full/uart_loopback.v
`timescale 1ns/1ps

module uart_loopback #(
    parameter integer CLKS_PER_BIT = 8
)(
    input  wire       clk,
    input  wire       rst_n,
    input  wire       start,
    input  wire [7:0] data_in,

    output wire       tx,
    output wire       tx_busy,
    output wire       tx_done,
    output wire       rx_valid,
    output wire [7:0] rx_data
);

    wire serial_line;

    assign tx = serial_line;

    uart_tx #(
        .CLKS_PER_BIT(CLKS_PER_BIT)
    ) u_tx (
        .clk(clk),
        .rst_n(rst_n),
        .data_in(data_in),
        .start(start),
        .tx(serial_line),
        .busy(tx_busy),
        .done(tx_done)
    );

    uart_rx #(
        .CLKS_PER_BIT(CLKS_PER_BIT)
    ) u_rx (
        .clk(clk),
        .rst_n(rst_n),
        .rx(serial_line),
        .data_out(rx_data),
        .valid(rx_valid)
    );

endmodule

archive/generated/vcd/uart_loopback.vcd
$version Generated by VerilatedVcd $end
$timescale 1ps $end
 $scope module TOP $end
  $var wire 1 . clk $end
  $var wire 1 / rst_n $end
  $var wire 1 0 start $end
  $var wire 8 1 data_in [7:0] $end
  $var wire 1 2 tx $end
  $var wire 1 3 tx_busy $end
  $var wire 1 4 tx_done $end
  $var wire 1 5 rx_valid $end
  $var wire 8 6 rx_data [7:0] $end
  $scope module uart_loopback $end
   $var wire 32 7 CLKS_PER_BIT [31:0] $end
   $var wire 1 . clk $end
   $var wire 1 / rst_n $end
   $var wire 1 0 start $end
   $var wire 8 1 data_in [7:0] $end
   $var wire 1 2 tx $end
   $var wire 1 3 tx_busy $end
   $var wire 1 4 tx_done $end
   $var wire 1 5 rx_valid $end
   $var wire 8 6 rx_data [7:0] $end
   $var wire 1 # serial_line $end
   $scope module u_rx $end
    $var wire 32 7 CLKS_PER_BIT [31:0] $end
    $var wire 1 . clk $end
    $var wire 1 / rst_n $end
    $var wire 1 # rx $end
    $var wire 8 6 data_out [7:0] $end
    $var wire 1 5 valid $end
    $var wire 2 8 ST_IDLE [1:0] $end
    $var wire 2 9 ST_START [1:0] $end
    $var wire 2 : ST_DATA [1:0] $end
    $var wire 2 ; ST_STOP [1:0] $end
    $var wire 2 $ st [1:0] $end
    $var wire 16 % clk_cnt [15:0] $end
    $var wire 3 & bit_idx [2:0] $end
    $var wire 8 ' shreg [7:0] $end
    $var wire 1 ( rx_s1 $end
    $var wire 1 ) rx_s2 $end
   $upscope $end
   $scope module u_tx $end
    $var wire 32 7 CLKS_PER_BIT [31:0] $end
    $var wire 1 . clk $end
    $var wire 1 / rst_n $end
    $var wire 8 1 data_in [7:0] $end
    $var wire 1 0 start $end
    $var wire 1 # tx $end
    $var wire 1 3 busy $end
    $var wire 1 4 done $end
    $var wire 2 8 ST_IDLE [1:0] $end
    $var wire 2 9 ST_START [1:0] $end
    $var wire 2 : ST_DATA [1:0] $end
    $var wire 2 ; ST_STOP [1:0] $end
    $var wire 16 < CLKS_PER_BIT_M1 [15:0] $end
    $var wire 2 * st [1:0] $end
    $var wire 16 + clk_cnt [15:0] $end
    $var wire 3 , bit_idx [2:0] $end
    $var wire 8 - shreg [7:0] $end
   $upscope $end
  $upscope $end
 $upscope $end
$enddefinitions $end


#0
0#
b00 $
b0000000000000000 %
b000 &
b00000000 '
0(
0)
b00 *
b0000000000000000 +
b000 ,
b00000000 -
0.
0/
00
b00000000 1
02
03
04
05
b00000000 6
b00000000000000000000000000001000 7
b00 8
b01 9
b10 :
b11 ;
b0000000000000111 <
#1
1#
1(
1)
1.
12
#2
0.
#3
1.
#4
0.
#5
1.
#6
0.
#7
1.
#8
0.
#9
1.
#10
0.
1/
#11
1.
#12
0.
#13
1.
#14
0.
#15
1.
#16
0.
#17
1.
#18
0.
#19
1.
#20
0.
10
b10100101 1
#21
b01 *
b10100101 -
1.
13
#22
0.
00
#23
0#
b0000000000000001 +
1.
02
#24
0.
#25
0(
b0000000000000010 +
1.
#26
0.
#27
0)
b0000000000000011 +
1.
#28
0.
#29
b01 $
b0000000000000100 +
1.
#30
0.
#31
b0000000000000001 %
b0000000000000101 +
1.
#32
0.
#33
b0000000000000010 %
b0000000000000110 +
1.
#34
0.
#35
b0000000000000011 %
b0000000000000111 +
1.
#36
0.
#37
b10 $
b0000000000000000 %
b10 *
b0000000000000000 +
1.
#38
0.
#39
1#
b0000000000000001 %
b0000000000000001 +
1.
12
#40
0.
#41
b0000000000000010 %
1(
b0000000000000010 +
1.
#42
0.
#43
b0000000000000011 %
1)
b0000000000000011 +
1.
#44
0.
#45
b0000000000000100 %
b0000000000000100 +
1.
#46
0.
#47
b0000000000000101 %
b0000000000000101 +
1.
#48
0.
#49
b0000000000000110 %
b0000000000000110 +
1.
#50
0.
#51
b0000000000000111 %
b0000000000000111 +
1.
#52
0.
#53
b0000000000000000 %
b001 &
b00000001 '
b0000000000000000 +
b001 ,
1.
#54
0.
#55
0#
b0000000000000001 %
b0000000000000001 +
1.
02
#56
0.
#57
b0000000000000010 %
0(
b0000000000000010 +
1.
#58
0.
#59
b0000000000000011 %
0)
b0000000000000011 +
1.
#60
0.
#61
b0000000000000100 %
b0000000000000100 +
1.
#62
0.
#63
b0000000000000101 %
b0000000000000101 +
1.
#64
0.
#65
b0000000000000110 %
b0000000000000110 +
1.
#66
0.
#67
b0000000000000111 %
b0000000000000111 +
1.
#68
0.
#69
b0000000000000000 %
b010 &
b0000000000000000 +
b010 ,
1.
#70
0.
#71
1#
b0000000000000001 %
b0000000000000001 +
1.
12
#72
0.
#73
b0000000000000010 %
1(
b0000000000000010 +
1.
#74
0.
#75
b0000000000000011 %
1)
b0000000000000011 +
1.
#76
0.
#77
b0000000000000100 %
b0000000000000100 +
1.
#78
0.
#79
b0000000000000101 %
b0000000000000101 +
1.
#80
0.
#81
b0000000000000110 %
b0000000000000110 +
1.
#82
0.
#83
b0000000000000111 %
b0000000000000111 +
1.
#84
0.
#85
b0000000000000000 %
b011 &
b00000101 '
b0000000000000000 +
b011 ,
1.
#86
0.
#87
0#
b0000000000000001 %
b0000000000000001 +
1.
02
#88
0.
#89
b0000000000000010 %
0(
b0000000000000010 +
1.
#90
0.
#91
b0000000000000011 %
0)
b0000000000000011 +
1.
#92
0.
#93
b0000000000000100 %
b0000000000000100 +
1.
#94
0.
#95
b0000000000000101 %
b0000000000000101 +
1.
#96
0.
#97
b0000000000000110 %
b0000000000000110 +
1.
#98
0.
#99
b0000000000000111 %
b0000000000000111 +
1.
#100
0.
#101
b0000000000000000 %
b100 &
b0000000000000000 +
b100 ,
1.
#102
0.
#103
b0000000000000001 %
b0000000000000001 +
1.
#104
0.
#105
b0000000000000010 %
b0000000000000010 +
1.
#106
0.
#107
b0000000000000011 %
b0000000000000011 +
1.
#108
0.
#109
b0000000000000100 %
b0000000000000100 +
1.
#110
0.
#111
b0000000000000101 %
b0000000000000101 +
1.
#112
0.
#113
b0000000000000110 %
b0000000000000110 +
1.
#114
0.
#115
b0000000000000111 %
b0000000000000111 +
1.
#116
0.
#117
b0000000000000000 %
b101 &
b0000000000000000 +
b101 ,
1.
#118
0.
#119
1#
b0000000000000001 %
b0000000000000001 +
1.
12
#120
0.
#121
b0000000000000010 %
1(
b0000000000000010 +
1.
#122
0.
#123
b0000000000000011 %
1)
b0000000000000011 +
1.
#124
0.
#125
b0000000000000100 %
b0000000000000100 +
1.
#126
0.
#127
b0000000000000101 %
b0000000000000101 +
1.
#128
0.
#129
b0000000000000110 %
b0000000000000110 +
1.
#130
0.
#131
b0000000000000111 %
b0000000000000111 +
1.
#132
0.
#133
b0000000000000000 %
b110 &
b00100101 '
b0000000000000000 +
b110 ,
1.
#134
0.
#135
0#
b0000000000000001 %
b0000000000000001 +
1.
02
#136
0.
#137
b0000000000000010 %
0(
b0000000000000010 +
1.
#138
0.
#139
b0000000000000011 %
0)
b0000000000000011 +
1.
#140
0.
#141
b0000000000000100 %
b0000000000000100 +
1.
#142
0.
#143
b0000000000000101 %
b0000000000000101 +
1.
#144
0.
#145
b0000000000000110 %
b0000000000000110 +
1.
#146
0.
#147
b0000000000000111 %
b0000000000000111 +
1.
#148
0.
#149
b0000000000000000 %
b111 &
b0000000000000000 +
b111 ,
1.
#150
0.
#151
1#
b0000000000000001 %
b0000000000000001 +
1.
12
#152
0.
#153
b0000000000000010 %
1(
b0000000000000010 +
1.
#154
0.
#155
b0000000000000011 %
1)
b0000000000000011 +
1.
#156
0.
#157
b0000000000000100 %
b0000000000000100 +
1.
#158
0.
#159
b0000000000000101 %
b0000000000000101 +
1.
#160
0.
#161
b0000000000000110 %
b0000000000000110 +
1.
#162
0.
#163
b0000000000000111 %
b0000000000000111 +
1.
#164
0.
#165
b11 $
b0000000000000000 %
b000 &
b10100101 '
b11 *
b0000000000000000 +
b000 ,
1.
#166
0.
#167
b0000000000000001 %
b0000000000000001 +
1.
#168
0.
#169
b0000000000000010 %
b0000000000000010 +
1.
#170
0.
#171
b0000000000000011 %
b0000000000000011 +
1.
#172
0.
#173
b0000000000000100 %
b0000000000000100 +
1.
#174
0.
#175
b0000000000000101 %
b0000000000000101 +
1.
#176
0.
#177
b0000000000000110 %
b0000000000000110 +
1.
#178
0.
#179
b0000000000000111 %
b0000000000000111 +
1.
#180
0.
#181
b00 $
b0000000000000000 %
b00 *
b0000000000000000 +
1.
14
15
b10100101 6
#182
0.
#183
1.
03
04
05
#184
0.
#185
1.
#186
0.
#187
1.
#188
0.
#189
1.
#190
0.
#191
1.
#192
0.
#193
1.
#194
0.
#195
1.
#196
0.
#197
1.
#198
0.
#199
1.
#200
0.
#201
1.
#202
0.
10
b00111100 1
#203
b01 *
b00111100 -
1.
13
#204
0.
00
#205
0#
b0000000000000001 +
1.
02
#206
0.
#207
0(
b0000000000000010 +
1.
#208
0.
#209
0)
b0000000000000011 +
1.
#210
0.
#211
b01 $
b0000000000000100 +
1.
#212
0.
#213
b0000000000000001 %
b0000000000000101 +
1.
#214
0.
#215
b0000000000000010 %
b0000000000000110 +
1.
#216
0.
#217
b0000000000000011 %
b0000000000000111 +
1.
#218
0.
#219
b10 $
b0000000000000000 %
b10 *
b0000000000000000 +
1.
#220
0.
#221
b0000000000000001 %
b0000000000000001 +
1.
#222
0.
#223
b0000000000000010 %
b0000000000000010 +
1.
#224
0.
#225
b0000000000000011 %
b0000000000000011 +
1.
#226
0.
#227
b0000000000000100 %
b0000000000000100 +
1.
#228
0.
#229
b0000000000000101 %
b0000000000000101 +
1.
#230
0.
#231
b0000000000000110 %
b0000000000000110 +
1.
#232
0.
#233
b0000000000000111 %
b0000000000000111 +
1.
#234
0.
#235
b0000000000000000 %
b001 &
b10100100 '
b0000000000000000 +
b001 ,
1.
#236
0.
#237
b0000000000000001 %
b0000000000000001 +
1.
#238
0.
#239
b0000000000000010 %
b0000000000000010 +
1.
#240
0.
#241
b0000000000000011 %
b0000000000000011 +
1.
#242
0.
#243
b0000000000000100 %
b0000000000000100 +
1.
#244
0.
#245
b0000000000000101 %
b0000000000000101 +
1.
#246
0.
#247
b0000000000000110 %
b0000000000000110 +
1.
#248
0.
#249
b0000000000000111 %
b0000000000000111 +
1.
#250
0.
#251
b0000000000000000 %
b010 &
b0000000000000000 +
b010 ,
1.
#252
0.
#253
1#
b0000000000000001 %
b0000000000000001 +
1.
12
#254
0.
#255
b0000000000000010 %
1(
b0000000000000010 +
1.
#256
0.
#257
b0000000000000011 %
1)
b0000000000000011 +
1.
#258
0.
#259
b0000000000000100 %
b0000000000000100 +
1.
#260
0.
#261
b0000000000000101 %
b0000000000000101 +
1.
#262
0.
#263
b0000000000000110 %
b0000000000000110 +
1.
#264
0.
#265
b0000000000000111 %
b0000000000000111 +
1.
#266
0.
#267
b0000000000000000 %
b011 &
b0000000000000000 +
b011 ,
1.
#268
0.
#269
b0000000000000001 %
b0000000000000001 +
1.
#270
0.
#271
b0000000000000010 %
b0000000000000010 +
1.
#272
0.
#273
b0000000000000011 %
b0000000000000011 +
1.
#274
0.
#275
b0000000000000100 %
b0000000000000100 +
1.
#276
0.
#277
b0000000000000101 %
b0000000000000101 +
1.
#278
0.
#279
b0000000000000110 %
b0000000000000110 +
1.
#280
0.
#281
b0000000000000111 %
b0000000000000111 +
1.
#282
0.
#283
b0000000000000000 %
b100 &
b10101100 '
b0000000000000000 +
b100 ,
1.
#284
0.
#285
b0000000000000001 %
b0000000000000001 +
1.
#286
0.
#287
b0000000000000010 %
b0000000000000010 +
1.
#288
0.
#289
b0000000000000011 %
b0000000000000011 +
1.
#290
0.
#291
b0000000000000100 %
b0000000000000100 +
1.
#292
0.
#293
b0000000000000101 %
b0000000000000101 +
1.
#294
0.
#295
b0000000000000110 %
b0000000000000110 +
1.
#296
0.
#297
b0000000000000111 %
b0000000000000111 +
1.
#298
0.
#299
b0000000000000000 %
b101 &
b10111100 '
b0000000000000000 +
b101 ,
1.
#300
0.
#301
b0000000000000001 %
b0000000000000001 +
1.
#302
0.
#303
b0000000000000010 %
b0000000000000010 +
1.
#304
0.
#305
b0000000000000011 %
b0000000000000011 +
1.
#306
0.
#307
b0000000000000100 %
b0000000000000100 +
1.
#308
0.
#309
b0000000000000101 %
b0000000000000101 +
1.
#310
0.
#311
b0000000000000110 %
b0000000000000110 +
1.
#312
0.
#313
b0000000000000111 %
b0000000000000111 +
1.
#314
0.
#315
b0000000000000000 %
b110 &
b0000000000000000 +
b110 ,
1.
#316
0.
#317
0#
b0000000000000001 %
b0000000000000001 +
1.
02
#318
0.
#319
b0000000000000010 %
0(
b0000000000000010 +
1.
#320
0.
#321
b0000000000000011 %
0)
b0000000000000011 +
1.
#322
0.
#323
b0000000000000100 %
b0000000000000100 +
1.
#324
0.
#325
b0000000000000101 %
b0000000000000101 +
1.
#326
0.
#327
b0000000000000110 %
b0000000000000110 +
1.
#328
0.
#329
b0000000000000111 %
b0000000000000111 +
1.
#330
0.
#331
b0000000000000000 %
b111 &
b0000000000000000 +
b111 ,
1.
#332
0.
#333
b0000000000000001 %
b0000000000000001 +
1.
#334
0.
#335
b0000000000000010 %
b0000000000000010 +
1.
#336
0.
#337
b0000000000000011 %
b0000000000000011 +
1.
#338
0.
#339
b0000000000000100 %
b0000000000000100 +
1.
#340
0.
#341
b0000000000000101 %
b0000000000000101 +
1.
#342
0.
#343
b0000000000000110 %
b0000000000000110 +
1.
#344
0.
#345
b0000000000000111 %
b0000000000000111 +
1.
#346
0.
#347
b11 $
b0000000000000000 %
b000 &
b00111100 '
b11 *
b0000000000000000 +
b000 ,
1.
#348
0.
#349
1#
b0000000000000001 %
b0000000000000001 +
1.
12
#350
0.
#351
b0000000000000010 %
1(
b0000000000000010 +
1.
#352
0.
#353
b0000000000000011 %
1)
b0000000000000011 +
1.
#354
0.
#355
b0000000000000100 %
b0000000000000100 +
1.
#356
0.
#357
b0000000000000101 %
b0000000000000101 +
1.
#358
0.
#359
b0000000000000110 %
b0000000000000110 +
1.
#360
0.
#361
b0000000000000111 %
b0000000000000111 +
1.
#362
0.
#363
b00 $
b0000000000000000 %
b00 *
b0000000000000000 +
1.
14
15
b00111100 6
#364
0.
#365
1.
03
04
05
